<annotation verified="yes">
	<folder>data</folder>
	<filename>img173.jpg</filename>
	<path>/home/ons/Bureau/data/img173.jpg</path>
	<source>
		<database>Unknown</database>
	</source>
	<size>
		<width>1280</width>
		<height>640</height>
		<depth>3</depth>
	</size>
	<segmented>0</segmented>
	<object>
		<name>person</name>
		<pose>Unspecified</pose>
		<truncated>0</truncated>
		<difficult>0</difficult>
		<bndbox>
			<xmin>57</xmin>
			<ymin>279</ymin>
			<xmax>236</xmax>
			<ymax>458</ymax>
		</bndbox>
	</object>
	<object>
		<name>person</name>
		<pose>Unspecified</pose>
		<truncated>0</truncated>
		<difficult>0</difficult>
		<bndbox>
			<xmin>249</xmin>
			<ymin>289</ymin>
			<xmax>397</xmax>
			<ymax>467</ymax>
		</bndbox>
	</object>
	<object>
		<name>person</name>
		<pose>Unspecified</pose>
		<truncated>0</truncated>
		<difficult>0</difficult>
		<bndbox>
			<xmin>379</xmin>
			<ymin>265</ymin>
			<xmax>516</xmax>
			<ymax>422</ymax>
		</bndbox>
	</object>
	<object>
		<name>person</name>
		<pose>Unspecified</pose>
		<truncated>0</truncated>
		<difficult>0</difficult>
		<bndbox>
			<xmin>694</xmin>
			<ymin>266</ymin>
			<xmax>814</xmax>
			<ymax>421</ymax>
		</bndbox>
	</object>
	<object>
		<name>person</name>
		<pose>Unspecified</pose>
		<truncated>0</truncated>
		<difficult>0</difficult>
		<bndbox>
			<xmin>856</xmin>
			<ymin>268</ymin>
			<xmax>1013</xmax>
			<ymax>452</ymax>
		</bndbox>
	</object>
	<object>
		<name>person</name>
		<pose>Unspecified</pose>
		<truncated>0</truncated>
		<difficult>0</difficult>
		<bndbox>
			<xmin>1020</xmin>
			<ymin>260</ymin>
			<xmax>1155</xmax>
			<ymax>413</ymax>
		</bndbox>
	</object>
	<object>
		<name>speaking</name>
		<pose>Unspecified</pose>
		<truncated>0</truncated>
		<difficult>0</difficult>
		<bndbox>
			<xmin>382</xmin>
			<ymin>259</ymin>
			<xmax>431</xmax>
			<ymax>364</ymax>
		</bndbox>
	</object>
	<object>
		<name>speaking</name>
		<pose>Unspecified</pose>
		<truncated>0</truncated>
		<difficult>0</difficult>
		<bndbox>
			<xmin>1017</xmin>
			<ymin>267</ymin>
			<xmax>1067</xmax>
			<ymax>369</ymax>
		</bndbox>
	</object>
</annotation>
