<annotation verified="yes">
	<folder>data</folder>
	<filename>vote225.jpg</filename>
	<path>/home/ons/Téléchargements/new_data_linagora-master-vote/vote/data/vote225.jpg</path>
	<source>
		<database>Unknown</database>
	</source>
	<size>
		<width>1280</width>
		<height>640</height>
		<depth>3</depth>
	</size>
	<segmented>0</segmented>
	<object>
		<name>voting</name>
		<pose>Unspecified</pose>
		<truncated>0</truncated>
		<difficult>0</difficult>
		<bndbox>
			<xmin>111</xmin>
			<ymin>284</ymin>
			<xmax>160</xmax>
			<ymax>367</ymax>
		</bndbox>
	</object>
	<object>
		<name>voting</name>
		<pose>Unspecified</pose>
		<truncated>0</truncated>
		<difficult>0</difficult>
		<bndbox>
			<xmin>380</xmin>
			<ymin>252</ymin>
			<xmax>440</xmax>
			<ymax>359</ymax>
		</bndbox>
	</object>
	<object>
		<name>voting</name>
		<pose>Unspecified</pose>
		<truncated>0</truncated>
		<difficult>0</difficult>
		<bndbox>
			<xmin>733</xmin>
			<ymin>280</ymin>
			<xmax>780</xmax>
			<ymax>358</ymax>
		</bndbox>
	</object>
	<object>
		<name>voting</name>
		<pose>Unspecified</pose>
		<truncated>0</truncated>
		<difficult>0</difficult>
		<bndbox>
			<xmin>876</xmin>
			<ymin>287</ymin>
			<xmax>907</xmax>
			<ymax>377</ymax>
		</bndbox>
	</object>
	<object>
		<name>person</name>
		<pose>Unspecified</pose>
		<truncated>0</truncated>
		<difficult>0</difficult>
		<bndbox>
			<xmin>96</xmin>
			<ymin>275</ymin>
			<xmax>256</xmax>
			<ymax>444</ymax>
		</bndbox>
	</object>
	<object>
		<name>person</name>
		<pose>Unspecified</pose>
		<truncated>0</truncated>
		<difficult>0</difficult>
		<bndbox>
			<xmin>363</xmin>
			<ymin>245</ymin>
			<xmax>521</xmax>
			<ymax>420</ymax>
		</bndbox>
	</object>
	<object>
		<name>person</name>
		<pose>Unspecified</pose>
		<truncated>0</truncated>
		<difficult>0</difficult>
		<bndbox>
			<xmin>717</xmin>
			<ymin>274</ymin>
			<xmax>842</xmax>
			<ymax>409</ymax>
		</bndbox>
	</object>
	<object>
		<name>person</name>
		<pose>Unspecified</pose>
		<truncated>0</truncated>
		<difficult>0</difficult>
		<bndbox>
			<xmin>870</xmin>
			<ymin>276</ymin>
			<xmax>990</xmax>
			<ymax>425</ymax>
		</bndbox>
	</object>
	<object>
		<name>person</name>
		<pose>Unspecified</pose>
		<truncated>0</truncated>
		<difficult>0</difficult>
		<bndbox>
			<xmin>1017</xmin>
			<ymin>287</ymin>
			<xmax>1107</xmax>
			<ymax>411</ymax>
		</bndbox>
	</object>
</annotation>
