<annotation>
	<folder>data_vote_test</folder>
	<filename>vtest181.jpg</filename>
	<path>/home/linagora/RICOH_THETA/new_data_test/data_vote_test/vtest181.jpg</path>
	<source>
		<database>Unknown</database>
	</source>
	<size>
		<width>1280</width>
		<height>640</height>
		<depth>3</depth>
	</size>
	<segmented>0</segmented>
	<object>
		<name>voting</name>
		<pose>Unspecified</pose>
		<truncated>0</truncated>
		<difficult>0</difficult>
		<bndbox>
			<xmin>371</xmin>
			<ymin>267</ymin>
			<xmax>426</xmax>
			<ymax>395</ymax>
		</bndbox>
	</object>
	<object>
		<name>person</name>
		<pose>Unspecified</pose>
		<truncated>0</truncated>
		<difficult>0</difficult>
		<bndbox>
			<xmin>356</xmin>
			<ymin>250</ymin>
			<xmax>526</xmax>
			<ymax>423</ymax>
		</bndbox>
	</object>
	<object>
		<name>person</name>
		<pose>Unspecified</pose>
		<truncated>0</truncated>
		<difficult>0</difficult>
		<bndbox>
			<xmin>697</xmin>
			<ymin>271</ymin>
			<xmax>844</xmax>
			<ymax>418</ymax>
		</bndbox>
	</object>
	<object>
		<name>person</name>
		<pose>Unspecified</pose>
		<truncated>0</truncated>
		<difficult>0</difficult>
		<bndbox>
			<xmin>989</xmin>
			<ymin>246</ymin>
			<xmax>1171</xmax>
			<ymax>437</ymax>
		</bndbox>
	</object>
	<object>
		<name>person</name>
		<pose>Unspecified</pose>
		<truncated>0</truncated>
		<difficult>0</difficult>
		<bndbox>
			<xmin>137</xmin>
			<ymin>268</ymin>
			<xmax>322</xmax>
			<ymax>470</ymax>
		</bndbox>
	</object>
	<object>
		<name>person</name>
		<pose>Unspecified</pose>
		<truncated>0</truncated>
		<difficult>0</difficult>
		<bndbox>
			<xmin>2</xmin>
			<ymin>286</ymin>
			<xmax>129</xmax>
			<ymax>428</ymax>
		</bndbox>
	</object>
	<object>
		<name>voting</name>
		<pose>Unspecified</pose>
		<truncated>0</truncated>
		<difficult>0</difficult>
		<bndbox>
			<xmin>768</xmin>
			<ymin>292</ymin>
			<xmax>810</xmax>
			<ymax>412</ymax>
		</bndbox>
	</object>
	<object>
		<name>voting</name>
		<pose>Unspecified</pose>
		<truncated>0</truncated>
		<difficult>0</difficult>
		<bndbox>
			<xmin>1013</xmin>
			<ymin>250</ymin>
			<xmax>1061</xmax>
			<ymax>368</ymax>
		</bndbox>
	</object>
	<object>
		<name>voting</name>
		<pose>Unspecified</pose>
		<truncated>0</truncated>
		<difficult>0</difficult>
		<bndbox>
			<xmin>141</xmin>
			<ymin>285</ymin>
			<xmax>183</xmax>
			<ymax>389</ymax>
		</bndbox>
	</object>
	<object>
		<name>voting</name>
		<pose>Unspecified</pose>
		<truncated>0</truncated>
		<difficult>0</difficult>
		<bndbox>
			<xmin>5</xmin>
			<ymin>312</ymin>
			<xmax>37</xmax>
			<ymax>409</ymax>
		</bndbox>
	</object>
</annotation>
